{"nodes": [{"id": "website_inspo_card_template", "label": "Inspo Website Card Template", "file_type": "code", "source_file": "_includes/inspo/website.html", "source_location": null, "source_url": null, "captured_at": null, "author": "Saptak Banerjee", "contributor": null}, {"id": "concept_jekyll_liquid", "label": "Jekyll / Liquid Templating", "file_type": "code", "source_file": "_includes/inspo/website.html", "source_location": null, "source_url": null, "captured_at": null, "author": null, "contributor": null}], "edges": [{"source": "website_inspo_card_template", "target": "concept_jekyll_liquid", "relation": "references", "confidence": "EXTRACTED", "confidence_score": 1.0, "source_file": "_includes/inspo/website.html", "source_location": "Liquid for loop and filters", "weight": 1.0}, {"source": "website_inspo_card_template", "target": "concept_inspo_page", "relation": "references", "confidence": "INFERRED", "confidence_score": 0.95, "source_file": "_includes/inspo/website.html", "source_location": null, "weight": 0.9}], "hyperedges": []}