{"nodes": [{"id": "note_spin", "label": "Spintronics: The Trillion-Dollar Bet Hidden Inside Your RAM Chip", "file_type": "document", "source_file": "notes/spin.md", "source_location": null, "source_url": null, "captured_at": "2026-02-03", "author": "Saptak Banerjee", "contributor": null}, {"id": "note_spin_mram", "label": "MRAM \u00e2\u20ac\u201d Magnetoresistive RAM (Spintronic Non-Volatile Memory)", "file_type": "document", "source_file": "notes/spin.md", "source_location": null, "source_url": null, "captured_at": null, "author": null, "contributor": null}, {"id": "note_spin_neuromorphic", "label": "Neuromorphic Computing via Spintronic Devices", "file_type": "document", "source_file": "notes/spin.md", "source_location": null, "source_url": null, "captured_at": null, "author": null, "contributor": null}, {"id": "note_spin_quantum", "label": "Quantum Computing \u00e2\u20ac\u201d Electron Spin as Qubit Substrate", "file_type": "document", "source_file": "notes/spin.md", "source_location": null, "source_url": null, "captured_at": null, "author": null, "contributor": null}], "edges": [{"source": "note_spin", "target": "note_spin_mram", "relation": "references", "confidence": "EXTRACTED", "confidence_score": 1.0, "source_file": "notes/spin.md", "source_location": null, "weight": 1.0}, {"source": "note_spin", "target": "note_spin_neuromorphic", "relation": "references", "confidence": "EXTRACTED", "confidence_score": 1.0, "source_file": "notes/spin.md", "source_location": null, "weight": 1.0}, {"source": "note_spin", "target": "note_spin_quantum", "relation": "references", "confidence": "EXTRACTED", "confidence_score": 1.0, "source_file": "notes/spin.md", "source_location": null, "weight": 1.0}, {"source": "note_spin", "target": "notes_page", "relation": "references", "confidence": "EXTRACTED", "confidence_score": 1.0, "source_file": "notes/spin.md", "source_location": null, "weight": 1.0}, {"source": "note_spin_neuromorphic", "target": "note_spin_quantum", "relation": "conceptually_related_to", "confidence": "EXTRACTED", "confidence_score": 1.0, "source_file": "notes/spin.md", "source_location": null, "weight": 0.85}, {"source": "note_spin", "target": "note_oi", "relation": "conceptually_related_to", "confidence": "INFERRED", "confidence_score": 0.75, "source_file": "notes/spin.md", "source_location": null, "weight": 0.75}, {"source": "note_spin", "target": "projects_quant_project", "relation": "conceptually_related_to", "confidence": "INFERRED", "confidence_score": 0.65, "source_file": "notes/spin.md", "source_location": null, "weight": 0.65}], "hyperedges": []}