{
  "nodes": [
    {
      "id": "p4_white_cracked_paint_texture",
      "label": "White Cracked Paint Texture on Wood",
      "file_type": "image",
      "source_file": "assets/img/p4.jpg",
      "source_location": null,
      "source_url": null,
      "captured_at": null,
      "author": null,
      "contributor": null,
      "description": "Close-up photographic texture of white cracked and peeling paint on a wooden surface. The weathered paint shows an extensive network of fine cracks and crazing patterns, revealing underlying wood grain. Monochromatic (black and white or heavily desaturated). Likely used as a background, overlay, or design texture element.",
      "tags": ["texture", "cracked paint", "wood", "weathered", "peeling", "white", "monochrome", "background", "design asset"],
      "visual_content": "AMBIGUOUS — purpose (decorative texture vs. documentary photo) not determinable from image alone",
      "dominant_colors": ["white", "light grey", "off-white"],
      "medium": "photography"
    }
  ],
  "edges": [],
  "hyperedges": [],
  "input_tokens": 0,
  "output_tokens": 0
}
